browser_manager/__init__.py
browser_manager/browser_manager_lib.py
screamshot/__init__.py
screamshot/browser_manager_script.py
screamshot/browser_opener_closer_script.py
screamshot/bytes_to_file_function.py
screamshot/bytes_to_png_function.py
screamshot/errors.py
screamshot/generate_bytes_img.py
screamshot/generate_bytes_img_functions.py
screamshot/py.typed
screamshot/screamshot_script.py
screamshot/serializer.py
screamshot/utils.py
tests/__init__.py
tests/generate_bytes_img_function_tests.py
tests/tests_generate_bytes_img_function.py
screamshot-0.1.12.dist-info/LICENSE
screamshot-0.1.12.dist-info/METADATA
screamshot-0.1.12.dist-info/WHEEL
screamshot-0.1.12.dist-info/entry_points.txt
screamshot-0.1.12.dist-info/top_level.txt
screamshot-0.1.12.dist-info/RECORD
