Metadata-Version: 2.1
Name: screamshot
Version: 0.1.12
Summary: Python library to capture screenshots of web applications or pages
Home-page: https://github.com/makinacorpus/screamshot
Author: Maxime Courtet & Félix Cloup
License: UNKNOWN
Platform: UNKNOWN
Classifier: Programming Language :: Python
Classifier: License :: OSI Approved :: BSD License
Classifier: Natural Language :: English
Classifier: Operating System :: OS Independent
Classifier: Programming Language :: Python :: 3.6
Requires-Dist: pyppeteer (==0.0.25)
Requires-Dist: requests (==2.21.0)
